[
  {
    "id": "1",
    "title": "Flutter + Firebase + SQL = DataConnect con Flutter",
    "img": "/events/devfest-25/speakers/speaker-1.webp",
    "name": "Fabián Varela Bonett",
    "description": "Firebase & Flutter"
  },
  {
    "id": "2",
    "title": "Como hacer despliegue a producción sin morir en el intento",
    "img": "/events/devfest-25/speakers/speaker-2.webp",
    "name": "Daniel Santiago Silva",
    "description": "DevOps & Cloud"
  },
  {
    "id": "3",
    "title": "Frontend en la era del edge",
    "img": "/events/devfest-25/speakers/speaker-3.webp",
    "name": "Nataly Paz",
    "description": "Desarrollo Web"
  },
  {
    "id": "4",
    "title": "Protegiendo y aprovechando la privacidad de la data: Federated Learning para Redes Neuronales",
    "img": "/events/devfest-25/speakers/speaker-4.webp",
    "name": "Diego Angulo Ramirez",
    "description": "IA/ML"
  },
  {
    "id": "5",
    "title": "People + AI Research (PAIR) Principles for AI Products",
    "img": "/events/devfest-25/speakers/speaker-5.webp",
    "name": "Gustavo Pacchi Villarroel",
    "description": "UX/UI"
  },
  {
    "id": "6",
    "title": "Android XR compose for XR Devices",
    "img": "/events/devfest-25/speakers/speaker-6.webp",
    "name": "Irvin Cossio Chavalier",
    "description": "Android, Desarrollo Web & XR - 5"
  }
]
